eeg_based_depression_detector/__init__.py
eeg_based_depression_detector/predictor.py
eeg_based_depression_detector/data/depression_detection_model.pkl
eeg_based_depression_detector-1.0.0.dist-info/METADATA
eeg_based_depression_detector-1.0.0.dist-info/WHEEL
eeg_based_depression_detector-1.0.0.dist-info/entry_points.txt
eeg_based_depression_detector-1.0.0.dist-info/top_level.txt
eeg_based_depression_detector-1.0.0.dist-info/RECORD
